statey/__init__.py
statey/exc.py
statey/executor.py
statey/fsm.py
statey/helpers.py
statey/hooks.py
statey/module.py
statey/plugin_installer.py
statey/provider.py
statey/registry.py
statey/resource.py
statey/state_manager.py
statey/task.py
statey/cli/__init__.py
statey/cli/__main__.py
statey/cli/controller.py
statey/cli/exc.py
statey/cli/inspect.py
statey/cli/log.py
statey/cli/requirements.py
statey/ext/__init__.py
statey/ext/graphviz.py
statey/ext/pulumi/__init__.py
statey/ext/pulumi/constants.py
statey/ext/pulumi/exc.py
statey/ext/pulumi/helpers.py
statey/ext/pulumi/plugin_installer.py
statey/ext/pulumi/provider.py
statey/ext/pulumi/provider_api.py
statey/ext/pulumi/resource.py
statey/plan/__init__.py
statey/plan/actions.py
statey/plan/migrators.py
statey/plan/plans.py
statey/syms/__init__.py
statey/syms/api.py
statey/syms/base.py
statey/syms/casters.py
statey/syms/diff.py
statey/syms/encoders.py
statey/syms/fmt.py
statey/syms/func.py
statey/syms/impl.py
statey/syms/impl_serializers.py
statey/syms/methods.py
statey/syms/model.py
statey/syms/namespace_serializers.py
statey/syms/object_.py
statey/syms/object_serializers.py
statey/syms/path.py
statey/syms/plugins.py
statey/syms/py_session.py
statey/syms/semantics.py
statey/syms/session.py
statey/syms/session_serializers.py
statey/syms/stack.py
statey/syms/type_serializers.py
statey/syms/types.py
statey/syms/utils.py
statey-0.0.9.dist-info/LICENSE.md
statey-0.0.9.dist-info/METADATA
statey-0.0.9.dist-info/WHEEL
statey-0.0.9.dist-info/entry_points.txt
statey-0.0.9.dist-info/top_level.txt
statey-0.0.9.dist-info/RECORD
