Metadata-Version: 2.1
Name: statey
Version: 0.0.9
Summary: Graph-based provisioning framework.
Home-page: https://github.com/cfeenstra67/statey
Author: Cam Feenstra
Author-email: cameron.l.feenstra@gmail.com
License: MIT
Platform: UNKNOWN
Classifier: Development Status :: 1 - Planning
Classifier: Programming Language :: Python :: 3
Classifier: License :: OSI Approved :: MIT License
Requires-Dist: marshmallow (==3.5.2)
Requires-Dist: pluggy (==0.13.1)
Requires-Dist: networkx (==2.4)
Requires-Dist: dataclasses (==0.7) ; python_version < "3.7"
Provides-Extra: all
Requires-Dist: fmt (==0.3.1) ; extra == 'all'
Requires-Dist: dill (==0.3.2) ; extra == 'all'
Requires-Dist: cloudpickle (==1.4.1) ; extra == 'all'
Requires-Dist: click (==7.1.2) ; extra == 'all'
Requires-Dist: asciidag (==0.2.0) ; extra == 'all'
Requires-Dist: pylumi (==1.2.2) ; extra == 'all'
Requires-Dist: jsonschema (==3.2.0) ; extra == 'all'
Requires-Dist: graphviz (==0.16) ; extra == 'all'
Provides-Extra: cli
Requires-Dist: click (==7.1.2) ; extra == 'cli'
Requires-Dist: asciidag (==0.2.0) ; extra == 'cli'
Provides-Extra: core
Requires-Dist: fmt (==0.3.1) ; extra == 'core'
Requires-Dist: click (==7.1.2) ; extra == 'core'
Requires-Dist: asciidag (==0.2.0) ; extra == 'core'
Provides-Extra: dev
Requires-Dist: black (==20.8b1) ; extra == 'dev'
Requires-Dist: twine ; extra == 'dev'
Requires-Dist: bumpversion ; extra == 'dev'
Requires-Dist: wheel ; extra == 'dev'
Provides-Extra: fmt
Requires-Dist: fmt (==0.3.1) ; extra == 'fmt'
Provides-Extra: graphviz
Requires-Dist: graphviz (==0.16) ; extra == 'graphviz'
Provides-Extra: pickle
Requires-Dist: dill (==0.3.2) ; extra == 'pickle'
Requires-Dist: cloudpickle (==1.4.1) ; extra == 'pickle'
Provides-Extra: pulumi
Requires-Dist: pylumi (==1.2.2) ; extra == 'pulumi'
Requires-Dist: jsonschema (==3.2.0) ; extra == 'pulumi'
Provides-Extra: tests
Requires-Dist: pytest ; extra == 'tests'
Requires-Dist: pytest-asyncio ; extra == 'tests'
Requires-Dist: fmt (==0.3.1) ; extra == 'tests'
Requires-Dist: click (==7.1.2) ; extra == 'tests'
Requires-Dist: asciidag (==0.2.0) ; extra == 'tests'
